pyzk2/__init__.py
pyzk2/attendance.py
pyzk2/base.py
pyzk2/const.py
pyzk2/exception.py
pyzk2/finger.py
pyzk2/user.py
pyzk2-0.2.dist-info/licenses/LICENSE
pyzk2-0.2.dist-info/licenses/LICENSE.txt
pyzk2-0.2.dist-info/METADATA
pyzk2-0.2.dist-info/WHEEL
pyzk2-0.2.dist-info/top_level.txt
pyzk2-0.2.dist-info/RECORD
