Metadata-Version: 2.4
Name: pyzk2
Version: 0.2
Summary: Forked version of fananimi/pyzk with latest changes.
Home-page: https://github.com/habibmhamed/pyzk2
Author: Habib Mhamadi
Author-email: habibmhamadi@gmail.com
License: LICENSE.txt
Keywords: zk,pyzk,pyzk2,zksoftware,attendance machine,fingerprint,biometrics,security
Requires-Python: >=3.6
License-File: LICENSE
License-File: LICENSE.txt
Dynamic: author
Dynamic: author-email
Dynamic: description
Dynamic: description-content-type
Dynamic: home-page
Dynamic: keywords
Dynamic: license
Dynamic: license-file
Dynamic: requires-python
Dynamic: summary
